MANIFEST.in
README.rst
setup.cfg
setup.py
medialog/.DS_Store
medialog/__init__.py
medialog.bergensiana.egg-info/PKG-INFO
medialog.bergensiana.egg-info/SOURCES.txt
medialog.bergensiana.egg-info/dependency_links.txt
medialog.bergensiana.egg-info/entry_points.txt
medialog.bergensiana.egg-info/namespace_packages.txt
medialog.bergensiana.egg-info/not-zip-safe
medialog.bergensiana.egg-info/requires.txt
medialog.bergensiana.egg-info/top_level.txt
medialog/bergensiana/.DS_Store
medialog/bergensiana/__init__.py
medialog/bergensiana/aboveportlets.pt
medialog/bergensiana/configure.zcml
medialog/bergensiana/dropdown.py
medialog/bergensiana/dropdown_recurse.pt
medialog/bergensiana/dropdown_sections.pt
medialog/bergensiana/interfaces.py
medialog/bergensiana/setuphandlers.py
medialog/bergensiana/topperportlets.pt
medialog/bergensiana/viewlets.py
medialog/bergensiana/browser/__init__.py
medialog/bergensiana/browser/configure.zcml
medialog/bergensiana/browser/left_sitemap.pt
medialog/bergensiana/browser/left_sitemap.py
medialog/bergensiana/browser/menu_sitemap.pt
medialog/bergensiana/browser/menu_sitemap.py
medialog/bergensiana/browser/mobile_sitemap.pt
medialog/bergensiana/browser/sitemap-item.pt
medialog/bergensiana/browser/visual-sitemap-item.pt
medialog/bergensiana/browser/visual_sitemap.pt
medialog/bergensiana/browser/visual_sitemap.py
medialog/bergensiana/portlets/__init__.py
medialog/bergensiana/portlets/sliderportlet.pt
medialog/bergensiana/portlets/sliderportlet.py
medialog/bergensiana/portlets/socialportlet.pt
medialog/bergensiana/portlets/socialportlet.py
medialog/bergensiana/profiles/.DS_Store
medialog/bergensiana/profiles/default/bergensiana_default.txt
medialog/bergensiana/profiles/default/browserlayer.xml
medialog/bergensiana/profiles/default/metadata.xml
medialog/bergensiana/profiles/default/portlets.xml
medialog/bergensiana/profiles/default/registry.xml
medialog/bergensiana/profiles/default/skins.xml
medialog/bergensiana/profiles/default/theme.xml
medialog/bergensiana/profiles/on_enable/bergensiana_enable.txt
medialog/bergensiana/profiles/on_enable/browserlayer.xml
medialog/bergensiana/profiles/on_enable/metadata.xml
medialog/bergensiana/profiles/on_enable/skins.xml
medialog/bergensiana/profiles/only_settings/registry.xml
medialog/bergensiana/profiles/portletsabove/metadata.xml
