Metadata-Version: 1.1
Name: medialog.bergensiana
Version: 0.2.4
Summary: An alternative theme for Plone 5.
Home-page: http://github.com/espenmn/medialog.bergensiana
Author: Espen Moe-Nilssen
Author-email: espen@medialog.no
License: GPL version 2
Keywords: web zope plone theme
Platform: UNKNOWN
Classifier: Environment :: Web Environment
Classifier: Development Status :: 4 - Beta
Classifier: Framework :: Plone :: 5.0
Classifier: Framework :: Zope2
Classifier: License :: OSI Approved :: GNU General Public License (GPL)
Classifier: Operating System :: OS Independent
Classifier: Programming Language :: Python
